pykrige/__init__.py
pykrige/_version.py
pykrige/ck.py
pykrige/compat.py
pykrige/compat_gstools.py
pykrige/core.py
pykrige/kriging_tools.py
pykrige/ok.py
pykrige/ok3d.py
pykrige/rk.py
pykrige/uk.py
pykrige/uk3d.py
pykrige/variogram_models.py
pykrige/lib/__init__.py
pykrige/lib/cok.cpython-312-aarch64-linux-gnu.so
pykrige/lib/variogram_models.cpython-312-aarch64-linux-gnu.so
pykrige-1.7.3.dist-info/METADATA
pykrige-1.7.3.dist-info/WHEEL
pykrige-1.7.3.dist-info/top_level.txt
pykrige-1.7.3.dist-info/RECORD
pykrige-1.7.3.dist-info/licenses/LICENSE
