Metadata-Version: 2.4
Name: PyKrige
Version: 1.7.3
Summary: Kriging Toolkit for Python.
Author-email: "Benjamin S. Murphy, Sebastian Müller" <info@geostat-framework.org>
Maintainer-email: "Sebastian Müller, Roman Yurchak" <info@geostat-framework.org>
License-Expression: BSD-3-Clause
Project-URL: Changelog, https://github.com/GeoStat-Framework/PyKrige/blob/main/CHANGELOG.md
Project-URL: Conda-Forge, https://anaconda.org/conda-forge/pykrige
Project-URL: Documentation, https://pykrige.readthedocs.io
Project-URL: Homepage, https://github.com/GeoStat-Framework/PyKrige
Project-URL: Source, https://github.com/GeoStat-Framework/PyKrige
Project-URL: Tracker, https://github.com/GeoStat-Framework/PyKrige/issues
Classifier: Development Status :: 5 - Production/Stable
Classifier: Intended Audience :: Developers
Classifier: Intended Audience :: End Users/Desktop
Classifier: Intended Audience :: Science/Research
Classifier: Natural Language :: English
Classifier: Operating System :: Unix
Classifier: Operating System :: Microsoft
Classifier: Operating System :: MacOS
Classifier: Programming Language :: Python
Classifier: Programming Language :: Python :: 3
Classifier: Programming Language :: Python :: 3 :: Only
Classifier: Programming Language :: Python :: 3.9
Classifier: Programming Language :: Python :: 3.10
Classifier: Programming Language :: Python :: 3.11
Classifier: Programming Language :: Python :: 3.12
Classifier: Programming Language :: Python :: 3.13
Classifier: Programming Language :: Python :: 3.14
Classifier: Topic :: Scientific/Engineering
Classifier: Topic :: Scientific/Engineering :: GIS
Classifier: Topic :: Scientific/Engineering :: Mathematics
Classifier: Topic :: Scientific/Engineering :: Physics
Classifier: Topic :: Utilities
Requires-Python: >=3.9
License-File: LICENSE
Requires-Dist: numpy>=1.20.0
Requires-Dist: scipy<2,>=1.5.4
Provides-Extra: doc
Requires-Dist: gstools<2,>=1.4; extra == "doc"
Requires-Dist: pillow; extra == "doc"
Requires-Dist: scikit-learn>=0.19; extra == "doc"
Requires-Dist: m2r2>=0.2.8; extra == "doc"
Requires-Dist: matplotlib>=3; extra == "doc"
Requires-Dist: numpydoc>=1.1; extra == "doc"
Requires-Dist: sphinx>=7; extra == "doc"
Requires-Dist: sphinx-gallery>=0.8; extra == "doc"
Requires-Dist: sphinx-rtd-theme>=2; extra == "doc"
Provides-Extra: plot
Requires-Dist: matplotlib<4,>=3; extra == "plot"
Provides-Extra: sklearn
Requires-Dist: scikit-learn>=0.19; extra == "sklearn"
Provides-Extra: test
Requires-Dist: pytest-cov>=3; extra == "test"
Requires-Dist: scikit-learn>=0.19; extra == "test"
Requires-Dist: gstools<2,>=1.4; extra == "test"
Provides-Extra: lint
Requires-Dist: black<24,>=23; extra == "lint"
Requires-Dist: pylint; extra == "lint"
Requires-Dist: isort[colors]; extra == "lint"
Requires-Dist: cython-lint; extra == "lint"
Dynamic: license-file
